trtm/__init__.py
trtm/__version__.py
trtm/cli.py
trtm/dat_file.py
trtm/export.py
trtm/scan.py
trtm/trtm.py
trtm/vims.py
trtm-0.1.2.dist-info/LICENSE.md
trtm-0.1.2.dist-info/METADATA
trtm-0.1.2.dist-info/WHEEL
trtm-0.1.2.dist-info/entry_points.txt
trtm-0.1.2.dist-info/top_level.txt
trtm-0.1.2.dist-info/RECORD
