Metadata-Version: 2.1
Name: trtm
Version: 0.1.2
Summary: Titan Radiative Transfer Model package
Home-page: https://github.com/seignovert/trtm
Author: Benoit Seignovert
Author-email: benoit.a.seignovert@jpl.nasa.gov
License: MIT
Platform: UNKNOWN
Classifier: License :: OSI Approved :: MIT License
Classifier: Programming Language :: Python :: 3
Classifier: Programming Language :: Python :: 3.6
Classifier: Programming Language :: Python :: 3.7
Classifier: Programming Language :: Python :: 3.8
Requires-Python: >=3.6
Requires-Dist: numpy
